graph_partition/.DS_Store
graph_partition/__init__.py
graph_partition/evaluation_metric/__init__.py
graph_partition/evaluation_metric/cluster_imbalance.py
graph_partition/evaluation_metric/evaluate_metric.py
graph_partition/evaluation_metric/getAgreementRateMetric.py
graph_partition/evaluation_metric/getClusterDiameter.py
graph_partition/evaluation_metric/getClusteringCost.py
graph_partition/gcn/.DS_Store
graph_partition/gcn/__init__.py
graph_partition/gcn/buildGraphConvolution.py
graph_partition/gcn/convolutionLayer.py
graph_partition/gcn/graphConvolutionNetwork.py
graph_partition/k_means/__init__.py
graph_partition/k_means/k_means.py
graph_partition/spectral_clustering/__init__.py
graph_partition/spectral_clustering/spectral_clustering.py
graph_partition-0.1.16.dist-info/LICENSE
graph_partition-0.1.16.dist-info/WHEEL
graph_partition-0.1.16.dist-info/METADATA
graph_partition-0.1.16.dist-info/RECORD
