Metadata-Version: 2.1
Name: graph-partition
Version: 0.1.16
Summary: Graph Partitioning Algorithms
License: MIT
Keywords: Graph Convolutional Network,Clustering,Spectral Clustering,Graph Neural Network
Author: somsubhra88
Requires-Python: >=3.9,<3.11
Classifier: License :: OSI Approved :: MIT License
Classifier: Programming Language :: Python :: 3
Classifier: Programming Language :: Python :: 3.10
Classifier: Programming Language :: Python :: 3.9
Requires-Dist: k-means-constrained (==0.7.1)
Requires-Dist: numpy (==1.23.1)
Requires-Dist: scikit-learn (==1.1.1)
Requires-Dist: scipy (>=1.8.1,<2.0.0)
Requires-Dist: torch (==1.12.0)
